asyncio_multisubscriber_queue/__init__.py
asyncio_multisubscriber_queue/py.typed
asyncio_multisubscriber_queue/queue.py
asyncio_multisubscriber_queue-0.4.1.dist-info/entry_points.txt
asyncio_multisubscriber_queue-0.4.1.dist-info/LICENSE
asyncio_multisubscriber_queue-0.4.1.dist-info/WHEEL
asyncio_multisubscriber_queue-0.4.1.dist-info/METADATA
asyncio_multisubscriber_queue-0.4.1.dist-info/RECORD
