Metadata-Version: 2.1
Name: asyncio-multisubscriber-queue
Version: 0.4.1
Summary: Allow a single producer to provide the same payload to multiple consumers simultaneously
Home-page: https://github.com/smithk86/asyncio-multisubscriber-queue
License: MIT
Author: Kyle Smith
Author-email: smithk86@smc3.com
Requires-Python: >=3.10,<4
Classifier: Framework :: AsyncIO
Classifier: Intended Audience :: Developers
Classifier: License :: OSI Approved :: MIT License
Classifier: Programming Language :: Python :: 3
Classifier: Programming Language :: Python :: 3.10
Classifier: Programming Language :: Python :: 3.11
Classifier: Topic :: Software Development :: Libraries :: Python Modules
Project-URL: Documentation, https://smithk86.github.io/asyncio-multisubscriber-queue
Project-URL: Repository, https://github.com/smithk86/asyncio-multisubscriber-queue
